
{
  "f": "all",
  "tr": 81,
  "status": 0,
  "errCode": "",
  "txt": "speaker",
  "csf": "2",
  "s": 0,
  "p": [
    {
      "startDate": "2013-11-29T04:44:37.000-06:00",
      "tn": "default",
      "evf": "0",
      "maxQty": 0,
      "itemFlag": "2",
      "promo": 0,
      "moa": 2,
      "ulpw": "$0.00",
      "prodid": "prod9230260",
      "endDate": null,
      "rc": 218,
      "suomsin": "",
      "id": "prod9230260",
      "iswti": 0,
      "pmns": "0",
      "ss": 0,
      "ft": [
        22,
        11
      ],
      "sva": [],
      "whyweloveit": "",
      "dp": "$149.88",
      "ds": 0,
      "mn": "EXPLORERBTM2BKXUS",
      "mp": "",
      "mo": "4",
      "ev": [],
      "cls": 0,
      "isn": 0,
      "promoContent": "",
      "n": "Block Rocker Explorer Sound System w/ Bluetooth (Various Colors) ",
      "sd": "<ul>\n\t<li>Stream music wirelessly from any Bluetooth device up to 100&nbsp;feet away<\/li>\n\t<li>Works w/ iPad, iPhone, Android, more<\/li>\n\t<li>Digital AM/FM radio w/ durable antenna<\/li>\n\t<li>Built-in rechargeable battery lasts up to 50&nbsp;hrs<\/li>\n\t<li>Recessed wheels and telescoping handle for portability<\/li>\n\t<li>Easy Pair links your NFC-enabled smartphone or tablet with a simple tap<\/li>\n<\/ul>\n",
      "minQty": 0,
      "se": [],
      "suomplu": "",
      "ip": "",
      "cs": "0",
      "li": "http://scene7.samsclub.com/is/image//samsclub/0081271501668_A",
      "r": 4.5688,
      "ld": "<p>Blast music wirelessly from smartphones, tablets, and more.<\/p>\n\n<p>Crank up your music whenever and wherever you want: Explorer Bluetooth is a powerful and flexible all-in-one sound system for mobile devices, MP3 players, microphones, and instruments. Explorer Bluetooth&#39;s wireless capability means you can keep your iPad, iPhone, Android or other Bluetooth music device right by your side as you blast your music. NFC-enabled smartphones or tablets can connect with just a simple tap using the Easy Pair feature.<\/p>\n\n<p>You can even listen to your favorite radio station or to the big game&mdash;just dial it in on Explorer Bluetooth&rsquo;s built-in AM/FM radio. The radio includes six presets so you can store your favorite radio stations. You can also plug in and crank up instruments, microphones and more. A high-quality microphone is included.<\/p>\n\n<p>With its built-in battery and charge indicator, Explorer Bluetooth lets you enjoy your music anywhere&mdash;indoors or outside&mdash;all day. A power cord is also included for nonstop music. You get powerful sound that&#39;s perfect for parties, BBQs, drive-in movies, family get-togethers, and more.<\/p>\n",
      "frs": 1,
      "sa": [
        {
          "vi": "http://scene7.samsclub.com/is/image/samsclub/0081271501470_S1",
          "moa": 2,
          "onlinePrice": {
            "smsglg": "",
            "showMsrp": 0,
            "ev": {},
            "msrpPrice": "",
            "ulpw": "$0.00",
            "suomplu": "",
            "finalPrice": "$149.88",
            "percentSaved": "",
            "suomsin": "",
            "iswti": 0,
            "pmns": "0",
            "listPrice": "$149.88",
            "smsgst": "",
            "pmxs": "0",
            "amountSaved": "",
            "pmsg": null,
            "savingType": ""
          },
          "ulpw": "$0.00",
          "id": "sku9754269",
          "cfgd": [{"Color": "Black"}],
          "subscribe": 0,
          "onlineInvLevels": {},
          "ss": 0,
          "ft": [
            22,
            11
          ],
          "dp": "$149.88",
          "sva": [],
          "ds": 0,
          "mp": "",
          "mo": "4",
          "cls": 0,
          "n": "Block Rocker Explorer Sound System w/Bluetooth",
          "pid": "prod9230260",
          "se": [],
          "in": 64737,
          "clubInv": {
            "viewOnly": 0,
            "maxQty": 0,
            "status": 0,
            "minQty": 0,
            "in": 0
          },
          "ip": "",
          "li": "http://scene7.samsclub.com/is/image//samsclub/0081271501470_A",
          "equalPrice": 0,
          "prc": "218",
          "am": "",
          "frs": 1,
          "forceLogin": 0,
          "onlineInv": {
            "viewOnly": 0,
            "maxQty": 0,
            "status": 0,
            "minQty": 0,
            "in": 64737
          },
          "clubPrice": {},
          "pr": 4.5688
        },
        {
          "vi": "http://scene7.samsclub.com/is/image/samsclub/0081271501668_S1",
          "moa": 2,
          "onlinePrice": {
            "smsglg": "",
            "showMsrp": 0,
            "ev": {},
            "msrpPrice": "",
            "ulpw": "$0.00",
            "suomplu": "",
            "finalPrice": "$149.88",
            "percentSaved": "",
            "suomsin": "",
            "iswti": 0,
            "pmns": "0",
            "listPrice": "$149.88",
            "smsgst": "",
            "pmxs": "0",
            "amountSaved": "",
            "pmsg": null,
            "savingType": ""
          },
          "ulpw": "$0.00",
          "id": "sku16374895",
          "cfgd": [{"Color": "Blue"}],
          "subscribe": 0,
          "onlineInvLevels": {},
          "ss": 0,
          "ft": [
            22,
            11
          ],
          "dp": "$149.88",
          "sva": [],
          "ds": 0,
          "mp": "",
          "mo": "4",
          "cls": 0,
          "n": "Block Rocker Explorer Sound System w/Bluetooth - Blue",
          "pid": "prod9230260",
          "se": [],
          "in": 60357,
          "clubInv": {
            "viewOnly": 0,
            "maxQty": 0,
            "status": 0,
            "minQty": 0,
            "in": 0
          },
          "ip": "",
          "li": "http://scene7.samsclub.com/is/image//samsclub/0081271501668_A",
          "equalPrice": 0,
          "prc": "218",
          "am": "",
          "frs": 1,
          "forceLogin": 0,
          "onlineInv": {
            "viewOnly": 0,
            "maxQty": 0,
            "status": 0,
            "minQty": 0,
            "in": 60357
          },
          "clubPrice": {},
          "pr": 4.5688
        },
        {
          "vi": "http://scene7.samsclub.com/is/image/samsclub/0081271501666_S1",
          "moa": 2,
          "onlinePrice": {},
          "ulpw": "$0.00",
          "id": "sku16374892",
          "cfgd": [{"Color": "Red"}],
          "subscribe": 0,
          "onlineInvLevels": {},
          "ss": 0,
          "ft": [11],
          "dp": "",
          "sva": [],
          "ds": 0,
          "mp": "",
          "mo": "4",
          "cls": 0,
          "n": "Block Rocker Explorer Sound System w/Bluetooth - Red",
          "pid": "prod9230260",
          "se": [],
          "in": 60335,
          "clubInv": {
            "viewOnly": 0,
            "maxQty": 0,
            "status": 0,
            "minQty": 0,
            "in": 0
          },
          "ip": "",
          "li": "http://scene7.samsclub.com/is/image//samsclub/0081271501666_A",
          "equalPrice": 0,
          "prc": "218",
          "am": "",
          "frs": 1,
          "forceLogin": 0,
          "onlineInv": {},
          "clubPrice": {},
          "pr": 4.5688
        }
      ],
      "forceLogin": 0,
      "pc": {
        "cid": "12360103",
        "cnm": "Back to Business Savings"
      },
      "pmxs": "0",
      "pt": "BOOK/CD/MOVIE",
      "brand": "Ion",
      "ElectronicDelivery": "n",
      "isVariant": 1,
      "prodrid": "prod9230260"
    },
    {
      "startDate": "2014-09-20T01:32:54.189-05:00",
      "tn": "default",
      "evf": "0",
      "maxQty": 0,
      "itemFlag": "3",
      "promo": 0,
      "moa": 2,
      "ulpw": "$0.00",
      "prodid": "prod15770308",
      "endDate": null,
      "rc": 76,
      "suomsin": "",
      "id": "prod15770308",
      "iswti": 0,
      "pmns": "0",
      "ss": 3,
      "ft": [0],
      "sva": [],
      "whyweloveit": "",
      "dp": "$14.91",
      "ds": 3,
      "mn": "70236",
      "mp": "",
      "mo": "4",
      "ev": [],
      "cls": 0,
      "isn": 0,
      "promoContent": "",
      "n": "Mobi Cube Bluetooth Speaker with Light Show",
      "sd": "<p>MOBI Cube brings the experience and passion of music through light.<\/p>\n",
      "minQty": 0,
      "se": [],
      "suomplu": "",
      "ip": "",
      "cs": "0",
      "li": "http://scene7.samsclub.com/is/image//samsclub/0089104070236_A",
      "r": 4.1039,
      "ld": "<p>Why listen to music through an uninspired device? Music is rich, blooming and moves with feeling. MOBI Cube brings the experience and passion of music through light. Uplifting your music experience through light and sound in a modern design.<br />\n<br />\n<b>Bluetooth Connectivity<\/b><br />\nWirelessly stream music from any Bluetooth enabled device.<br />\n<br />\n<b>LED Lights Show<\/b><br />\nFeatures a Multi LED light show. 5 light modes, giving you a new experience to enjoy your music.<br />\n<br />\n<b>Auxiliary Wired Input<\/b><br />\nConnect to all other Audio devices.<br />\n<br />\n<b>6-Hour Rechargeable Li-Ion Battery<\/b><br />\nConvenient Rechargeable battery for portability and extended play time.<\/p>\n",
      "frs": 1,
      "sa": [{
        "vi": "",
        "moa": 2,
        "onlinePrice": {
          "smsglg": "",
          "showMsrp": 0,
          "ev": {},
          "msrpPrice": "",
          "ulpw": "$0.00",
          "suomplu": "",
          "finalPrice": "$14.91",
          "percentSaved": "",
          "suomsin": "",
          "iswti": 0,
          "pmns": "0",
          "listPrice": "$14.91",
          "smsgst": "",
          "pmxs": "0",
          "amountSaved": "",
          "pmsg": null,
          "savingType": ""
        },
        "ulpw": "$0.00",
        "id": "sku16284029",
        "cfgd": [],
        "subscribe": 0,
        "onlineInvLevels": {},
        "ss": 3,
        "ft": [0],
        "dp": "$14.91",
        "sva": [],
        "ds": 3,
        "mp": "",
        "mo": "4",
        "cls": 0,
        "n": "Mobi Cube Bluetooth Speaker with Light Show",
        "pid": "prod15770308",
        "se": [],
        "in": 783,
        "clubInv": {},
        "ip": "",
        "li": "http://scene7.samsclub.com/is/image//samsclub/0089104070236_A",
        "equalPrice": 0,
        "prc": "76",
        "am": "",
        "frs": 1,
        "forceLogin": 0,
        "onlineInv": {
          "viewOnly": 0,
          "maxQty": 0,
          "status": 3,
          "minQty": 0,
          "in": 783
        },
        "clubPrice": {},
        "pr": 4.1039
      }],
      "forceLogin": 0,
      "pc": {
        "cid": "12250129",
        "cnm": "Tech Gifts Under $100 - offline"
      },
      "pmxs": "0",
      "pt": "NORMAL ITEM",
      "brand": "MOBI",
      "ElectronicDelivery": "n",
      "isVariant": 0,
      "prodrid": "prod15770308"
    },
    {
      "startDate": "2013-08-08T02:58:11.000-05:00",
      "tn": "default",
      "evf": "0",
      "maxQty": 0,
      "itemFlag": "3",
      "promo": 0,
      "moa": 2,
      "ulpw": "$0.00",
      "prodid": "prod11350152",
      "endDate": null,
      "rc": 124,
      "suomsin": "",
      "id": "prod11350152",
      "iswti": 0,
      "pmns": "0",
      "ss": 3,
      "ft": [0],
      "sva": [],
      "whyweloveit": "",
      "dp": "$24.86",
      "ds": 3,
      "mn": "SP880RD",
      "mp": "",
      "mo": "4",
      "ev": [],
      "cls": 0,
      "isn": 0,
      "promoContent": "",
      "n": "808 CANZ Portable Wireless Speaker - Various Colors",
      "sd": "<p><span style=\"color: #ff0000\"><b>Free standard shipping for online orders.<\/b><\/span><\/p>\n\n<p>808 CANZ wireless Bluetooth speakers provide big sound in a little package,&nbsp;featuring a rechargeable lithium polymer battery&nbsp;for 6 hours of playtime at normal volume from a single charge.<\/p>\n",
      "minQty": 0,
      "se": [],
      "suomplu": "",
      "ip": "",
      "cs": "0",
      "li": "http://scene7.samsclub.com/is/image//samsclub/0004447611476_A",
      "r": 4.632,
      "ld": "It's pretty simple. 808 is all about street smarts, cutting-edge audio technology, and intelligently priced products for the discerning enthusiast. Our goal is to make gear that works as well as it looks. We set out to make stuff that we'd want to use ourselves. No hype. No silly celebrity endorsements. If it says \"808\" on it, you can trust that it will not only enhance your listening experience – it will let you hear your music like never before.",
      "frs": 1,
      "sa": [
        {
          "vi": "http://scene7.samsclub.com/is/image/samsclub/0004447611476_S1",
          "moa": 2,
          "onlinePrice": {
            "smsglg": "",
            "showMsrp": 0,
            "ev": {},
            "msrpPrice": "",
            "ulpw": "$0.00",
            "suomplu": "",
            "finalPrice": "$24.86",
            "percentSaved": "",
            "suomsin": "",
            "iswti": 0,
            "pmns": "0",
            "listPrice": "$24.86",
            "smsgst": "",
            "pmxs": "0",
            "amountSaved": "",
            "pmsg": null,
            "savingType": ""
          },
          "ulpw": "$0.00",
          "id": "sku11864153",
          "cfgd": [{"Color": "Red"}],
          "subscribe": 0,
          "onlineInvLevels": {},
          "ss": 3,
          "ft": [0],
          "dp": "$24.86",
          "sva": [],
          "ds": 3,
          "mp": "",
          "mo": "4",
          "cls": 0,
          "n": "808 CANZ Portable Wireless Speaker - Red",
          "pid": "prod11350152",
          "se": [],
          "in": 161897,
          "clubInv": {},
          "ip": "",
          "li": "http://scene7.samsclub.com/is/image//samsclub/0004447611476_A",
          "equalPrice": 0,
          "prc": "124",
          "am": "",
          "frs": 1,
          "forceLogin": 0,
          "onlineInv": {
            "viewOnly": 0,
            "maxQty": 0,
            "status": 3,
            "minQty": 0,
            "in": 161897
          },
          "clubPrice": {},
          "pr": 4.632
        },
        {
          "vi": "http://scene7.samsclub.com/is/image/samsclub/0004447611475_S1",
          "moa": 2,
          "onlinePrice": {
            "smsglg": "",
            "showMsrp": 0,
            "ev": {},
            "msrpPrice": "",
            "ulpw": "$0.00",
            "suomplu": "",
            "finalPrice": "$24.86",
            "percentSaved": "",
            "suomsin": "",
            "iswti": 0,
            "pmns": "0",
            "listPrice": "$24.86",
            "smsgst": "",
            "pmxs": "0",
            "amountSaved": "",
            "pmsg": null,
            "savingType": ""
          },
          "ulpw": "$0.00",
          "id": "sku11864152",
          "cfgd": [{"Color": "Blue"}],
          "subscribe": 0,
          "onlineInvLevels": {},
          "ss": 3,
          "ft": [0],
          "dp": "$24.86",
          "sva": [],
          "ds": 3,
          "mp": "",
          "mo": "4",
          "cls": 0,
          "n": "808 CANZ Portable Wireless Speaker - Blue",
          "pid": "prod11350152",
          "se": [],
          "in": 161890,
          "clubInv": {},
          "ip": "",
          "li": "http://scene7.samsclub.com/is/image//samsclub/0004447611475_A",
          "equalPrice": 0,
          "prc": "124",
          "am": "",
          "frs": 1,
          "forceLogin": 0,
          "onlineInv": {
            "viewOnly": 0,
            "maxQty": 0,
            "status": 3,
            "minQty": 0,
            "in": 161890
          },
          "clubPrice": {},
          "pr": 4.632
        },
        {
          "vi": "http://scene7.samsclub.com/is/image/samsclub/0004447611474_S1",
          "moa": 2,
          "onlinePrice": {
            "smsglg": "",
            "showMsrp": 0,
            "ev": {},
            "msrpPrice": "",
            "ulpw": "$0.00",
            "suomplu": "",
            "finalPrice": "$24.86",
            "percentSaved": "",
            "suomsin": "",
            "iswti": 0,
            "pmns": "0",
            "listPrice": "$24.86",
            "smsgst": "",
            "pmxs": "0",
            "amountSaved": "",
            "pmsg": null,
            "savingType": ""
          },
          "ulpw": "$0.00",
          "id": "sku11864151",
          "cfgd": [{"Color": "Silver"}],
          "subscribe": 0,
          "onlineInvLevels": {},
          "ss": 3,
          "ft": [0],
          "dp": "$24.86",
          "sva": [],
          "ds": 3,
          "mp": "",
          "mo": "4",
          "cls": 0,
          "n": "808 CANZ Portable Wireless Speaker - Silver",
          "pid": "prod11350152",
          "se": [],
          "in": 161880,
          "clubInv": {},
          "ip": "",
          "li": "http://scene7.samsclub.com/is/image//samsclub/0004447611474_A",
          "equalPrice": 0,
          "prc": "124",
          "am": "",
          "frs": 1,
          "forceLogin": 0,
          "onlineInv": {
            "viewOnly": 0,
            "maxQty": 0,
            "status": 3,
            "minQty": 0,
            "in": 161880
          },
          "clubPrice": {},
          "pr": 4.632
        },
        {
          "vi": "http://scene7.samsclub.com/is/image/samsclub/0040639464289_S1",
          "moa": 2,
          "onlinePrice": {
            "smsglg": "",
            "showMsrp": 0,
            "ev": {},
            "msrpPrice": "",
            "ulpw": "$0.00",
            "suomplu": "",
            "finalPrice": "$24.86",
            "percentSaved": "",
            "suomsin": "",
            "iswti": 0,
            "pmns": "0",
            "listPrice": "$24.86",
            "smsgst": "",
            "pmxs": "0",
            "amountSaved": "",
            "pmsg": null,
            "savingType": ""
          },
          "ulpw": "$0.00",
          "id": "sku16264621",
          "cfgd": [{"Color": "Black"}],
          "subscribe": 0,
          "onlineInvLevels": {},
          "ss": 3,
          "ft": [0],
          "dp": "$24.86",
          "sva": [],
          "ds": 3,
          "mp": "",
          "mo": "4",
          "cls": 0,
          "n": "808 CANZ Portable Wireless Speaker - Black",
          "pid": "prod11350152",
          "se": [],
          "in": 946428,
          "clubInv": {},
          "ip": "",
          "li": "http://scene7.samsclub.com/is/image//samsclub/0040639464289_A",
          "equalPrice": 0,
          "prc": "124",
          "am": "",
          "frs": 1,
          "forceLogin": 0,
          "onlineInv": {
            "viewOnly": 0,
            "maxQty": 0,
            "status": 3,
            "minQty": 0,
            "in": 946428
          },
          "clubPrice": {},
          "pr": 4.632
        },
        {
          "vi": "http://scene7.samsclub.com/is/image/samsclub/0004447612311_S1",
          "moa": 2,
          "onlinePrice": {
            "smsglg": "",
            "showMsrp": 0,
            "ev": {},
            "msrpPrice": "",
            "ulpw": "$0.00",
            "suomplu": "",
            "finalPrice": "$24.88",
            "percentSaved": "",
            "suomsin": "",
            "iswti": 0,
            "pmns": "0",
            "listPrice": "$24.88",
            "smsgst": "",
            "pmxs": "0",
            "amountSaved": "",
            "pmsg": null,
            "savingType": ""
          },
          "ulpw": "$0.00",
          "id": "sku18954414",
          "cfgd": [{"Color": "Purple"}],
          "subscribe": 0,
          "onlineInvLevels": {},
          "ss": 3,
          "ft": [
            0,
            11
          ],
          "dp": "$24.88",
          "sva": [],
          "ds": 3,
          "mp": "",
          "mo": "4",
          "cls": 0,
          "n": "808 CANZ Portable Wireless Speaker- Purple",
          "pid": "prod11350152",
          "se": [],
          "in": 848995,
          "clubInv": {
            "viewOnly": 0,
            "maxQty": 0,
            "status": 0,
            "minQty": 0,
            "in": 0
          },
          "ip": "",
          "li": "http://scene7.samsclub.com/is/image//samsclub/0004447612311_A",
          "equalPrice": 0,
          "prc": "124",
          "am": "",
          "frs": 1,
          "forceLogin": 0,
          "onlineInv": {
            "viewOnly": 0,
            "maxQty": 0,
            "status": 3,
            "minQty": 0,
            "in": 848995
          },
          "clubPrice": {},
          "pr": 4.632
        }
      ],
      "forceLogin": 0,
      "pc": {
        "cid": "11980103",
        "cnm": "Bluetooth Speakers"
      },
      "pmxs": "0",
      "pt": "NORMAL ITEM",
      "brand": "808",
      "ElectronicDelivery": "n",
      "isVariant": 1,
      "prodrid": "prod11350152"
    },
    {
      "startDate": "2015-02-10T01:47:50.871-06:00",
      "tn": "default",
      "evf": "0",
      "maxQty": 0,
      "itemFlag": "0",
      "promo": 0,
      "moa": 2,
      "ulpw": "$0.00",
      "prodid": "prod17290986",
      "endDate": null,
      "rc": 16,
      "suomsin": "",
      "id": "prod17290986",
      "iswti": 0,
      "pmns": "0",
      "ss": 3,
      "ft": [
        0,
        11
      ],
      "sva": [],
      "whyweloveit": "",
      "dp": "$169.88",
      "ds": 3,
      "mn": "Rockin' Roller",
      "mp": "",
      "mo": "4",
      "ev": [],
      "cls": 0,
      "isn": 0,
      "promoContent": "",
      "n": "Monster Rockin' Roller Portable Indoor/Outdoor Wireless Speaker",
      "sd": "<ul>\n\t<li>Easy Bluetooth connect&nbsp;<\/li>\n\t<li>Rechargable battery lasts up to 75 hours&nbsp;<\/li>\n\t<li>FM radio&nbsp;<\/li>\n\t<li>Weather-resistant<\/li>\n<\/ul>\n",
      "minQty": 0,
      "se": [],
      "suomplu": "",
      "ip": "",
      "cs": "0",
      "li": "http://scene7.samsclub.com/is/image//samsclub/0082739652642_A",
      "r": 4.6,
      "ld": "<p><span style=\"line-height: 1.6em\">Rock on with Monster Rockin&#39; Roller Portable Indoor/Outdoor Wireless Speaker! With&nbsp;Bluetooth Connect and FM radio, you can listen to your music&nbsp;wherever you are. Monster Rockin&#39; Roller has you covered with two extra outlets built in, so you can recharge your phone and other devices while you rock on!&nbsp;LED lights are great for&nbsp;easy&nbsp;viewing at night, and a built-in rechargable battery that lasts up to 75 hours provides you with endless tunes.&nbsp;<\/span><\/p>\n",
      "frs": 0,
      "sa": [{
        "vi": "",
        "moa": 2,
        "onlinePrice": {
          "smsglg": "",
          "showMsrp": 0,
          "ev": {},
          "msrpPrice": "",
          "ulpw": "$0.00",
          "suomplu": "",
          "finalPrice": "$169.88",
          "percentSaved": "",
          "suomsin": "",
          "iswti": 0,
          "pmns": "0",
          "listPrice": "$169.88",
          "smsgst": "",
          "pmxs": "0",
          "amountSaved": "",
          "pmsg": null,
          "savingType": ""
        },
        "ulpw": "$0.00",
        "id": "sku17804986",
        "cfgd": [],
        "subscribe": 0,
        "onlineInvLevels": {},
        "ss": 3,
        "ft": [
          0,
          11
        ],
        "dp": "$169.88",
        "sva": [],
        "ds": 3,
        "mp": "",
        "mo": "4",
        "cls": 0,
        "n": "Monster Rockin' Roller Portable Indoor/Outdoor Wireless Speaker",
        "pid": "prod17290986",
        "se": [],
        "in": 486032,
        "clubInv": {
          "viewOnly": 0,
          "maxQty": 0,
          "status": 0,
          "minQty": 0,
          "in": 0
        },
        "ip": "",
        "li": "http://scene7.samsclub.com/is/image//samsclub/0082739652642_A",
        "equalPrice": 0,
        "prc": "16",
        "am": "",
        "frs": 0,
        "forceLogin": 0,
        "onlineInv": {
          "viewOnly": 0,
          "maxQty": 0,
          "status": 3,
          "minQty": 0,
          "in": 486032
        },
        "clubPrice": {},
        "pr": 4.6
      }],
      "forceLogin": 0,
      "pc": {
        "cid": "12390113",
        "cnm": "Office Instant Savings"
      },
      "pmxs": "0",
      "pt": "NORMAL ITEM",
      "brand": "Monster",
      "ElectronicDelivery": "n",
      "isVariant": 0,
      "prodrid": "prod17290986"
    },
    {
      "startDate": "2015-01-01T01:45:00.318-06:00",
      "tn": "default",
      "evf": "0",
      "maxQty": 0,
      "itemFlag": "",
      "promo": 0,
      "moa": 2,
      "ulpw": "$0.00",
      "prodid": "prod16880030",
      "endDate": null,
      "rc": 1,
      "suomsin": "",
      "id": "prod16880030",
      "iswti": 0,
      "pmns": "0",
      "ss": 3,
      "ft": [
        0,
        11
      ],
      "sva": [],
      "whyweloveit": "",
      "dp": "$69.88",
      "ds": 3,
      "mn": "B705TBP",
      "mp": "$99.99",
      "mo": "2",
      "ev": [],
      "cls": 0,
      "isn": 0,
      "promoContent": "",
      "n": "Braven 705 Portable Wireless Speaker - Various Colors",
      "sd": "<p>Precision engineered with a shock-absorbent thermoplastic exterior and sleek finish, the Braven 705 Speaker is offered in a wide variety of colors to match your personal style.<\/p>\n",
      "minQty": 0,
      "se": [],
      "suomplu": "",
      "ip": "",
      "cs": "0",
      "li": "http://scene7.samsclub.com/is/image//samsclub/0081772901129_A",
      "r": 5,
      "ld": "<p>Lightweight portability meets big sound with the powerful Braven 705 Speaker. Custom high-fidelity audio drivers deliver room-filling sound to your music, media, conference calls and more. For a powerful, immersive left and right stereo experience, pair any two Braven 7-Series speakers together using Braven&#39;s highly-acclaimed TrueWireless&trade; Technology. Precision engineered with a shock-absorbent thermoplastic exterior and sleek finish, the Braven 705 Speaker is offered in a wide variety of colors to match your personal style.<\/p>\n",
      "frs": 1,
      "sa": [
        {
          "vi": "http://scene7.samsclub.com/is/image/samsclub/0081772901128_S1",
          "moa": 2,
          "onlinePrice": {
            "smsglg": "",
            "showMsrp": 0,
            "ev": {},
            "msrpPrice": "",
            "ulpw": "$0.00",
            "suomplu": "",
            "finalPrice": "$69.88",
            "percentSaved": "",
            "suomsin": "",
            "iswti": 0,
            "pmns": "0",
            "listPrice": "$69.88",
            "smsgst": "",
            "pmxs": "0",
            "amountSaved": "",
            "pmsg": null,
            "savingType": ""
          },
          "ulpw": "$0.00",
          "id": "sku17104262",
          "cfgd": [{"Color": "Gray"}],
          "subscribe": 0,
          "onlineInvLevels": {},
          "ss": 0,
          "ft": [
            22,
            11
          ],
          "dp": "$69.88",
          "sva": [],
          "ds": 0,
          "mp": "$99.99",
          "mo": "2",
          "cls": 0,
          "n": "Braven 705 Portable Wireless Speaker - Gray",
          "pid": "prod16880030",
          "se": [],
          "in": 342268,
          "clubInv": {
            "viewOnly": 0,
            "maxQty": 0,
            "status": 0,
            "minQty": 0,
            "in": 0
          },
          "ip": "",
          "li": "http://scene7.samsclub.com/is/image//samsclub/0081772901128_A",
          "equalPrice": 0,
          "prc": "1",
          "am": "",
          "frs": 1,
          "forceLogin": 0,
          "onlineInv": {
            "viewOnly": 0,
            "maxQty": 0,
            "status": 0,
            "minQty": 0,
            "in": 422172
          },
          "clubPrice": {},
          "pr": 5
        },
        {
          "vi": "http://scene7.samsclub.com/is/image/samsclub/0081772901124_S1",
          "moa": 2,
          "onlinePrice": {
            "smsglg": "",
            "showMsrp": 0,
            "ev": {},
            "msrpPrice": "",
            "ulpw": "$0.00",
            "suomplu": "",
            "finalPrice": "$69.88",
            "percentSaved": "",
            "suomsin": "",
            "iswti": 0,
            "pmns": "0",
            "listPrice": "$69.88",
            "smsgst": "",
            "pmxs": "0",
            "amountSaved": "",
            "pmsg": null,
            "savingType": ""
          },
          "ulpw": "$0.00",
          "id": "sku17394021",
          "cfgd": [{"Color": "Magenta"}],
          "subscribe": 0,
          "onlineInvLevels": {},
          "ss": 0,
          "ft": [
            22,
            11
          ],
          "dp": "$69.88",
          "sva": [],
          "ds": 0,
          "mp": "$99.99",
          "mo": "2",
          "cls": 0,
          "n": "Braven 705 Portable Wireless Speaker - Magenta",
          "pid": "prod16880030",
          "se": [],
          "in": 450411,
          "clubInv": {
            "viewOnly": 0,
            "maxQty": 0,
            "status": 0,
            "minQty": 0,
            "in": 0
          },
          "ip": "",
          "li": "http://scene7.samsclub.com/is/image//samsclub/0081772901124_A",
          "equalPrice": 0,
          "prc": "1",
          "am": "",
          "frs": 1,
          "forceLogin": 0,
          "onlineInv": {
            "viewOnly": 0,
            "maxQty": 0,
            "status": 0,
            "minQty": 0,
            "in": 422180
          },
          "clubPrice": {},
          "pr": 5
        },
        {
          "vi": "http://scene7.samsclub.com/is/image/samsclub/0081772901129_S1",
          "moa": 2,
          "onlinePrice": {
            "smsglg": "",
            "showMsrp": 0,
            "ev": {},
            "msrpPrice": "",
            "ulpw": "$0.00",
            "suomplu": "",
            "finalPrice": "$69.88",
            "percentSaved": "",
            "suomsin": "",
            "iswti": 0,
            "pmns": "0",
            "listPrice": "$69.88",
            "smsgst": "",
            "pmxs": "0",
            "amountSaved": "",
            "pmsg": null,
            "savingType": ""
          },
          "ulpw": "$0.00",
          "id": "sku17594274",
          "cfgd": [{"Color": "Teal"}],
          "subscribe": 0,
          "onlineInvLevels": {},
          "ss": 3,
          "ft": [
            0,
            11
          ],
          "dp": "$69.88",
          "sva": [],
          "ds": 3,
          "mp": "$99.99",
          "mo": "2",
          "cls": 0,
          "n": "Braven 705 Portable Wireless Speaker - Teal",
          "pid": "prod16880030",
          "se": [],
          "in": 344838,
          "clubInv": {
            "viewOnly": 0,
            "maxQty": 0,
            "status": 0,
            "minQty": 0,
            "in": 0
          },
          "ip": "",
          "li": "http://scene7.samsclub.com/is/image//samsclub/0081772901129_A",
          "equalPrice": 0,
          "prc": "1",
          "am": "",
          "frs": 1,
          "forceLogin": 0,
          "onlineInv": {
            "viewOnly": 0,
            "maxQty": 0,
            "status": 3,
            "minQty": 0,
            "in": 422228
          },
          "clubPrice": {},
          "pr": 5
        },
        {
          "vi": "http://scene7.samsclub.com/is/image/samsclub/0081772901123_S1",
          "moa": 2,
          "onlinePrice": {
            "smsglg": "",
            "showMsrp": 0,
            "ev": {},
            "msrpPrice": "",
            "ulpw": "$0.00",
            "suomplu": "",
            "finalPrice": "$69.88",
            "percentSaved": "",
            "suomsin": "",
            "iswti": 0,
            "pmns": "0",
            "listPrice": "$69.88",
            "smsgst": "",
            "pmxs": "0",
            "amountSaved": "",
            "pmsg": null,
            "savingType": ""
          },
          "ulpw": "$0.00",
          "id": "sku17664529",
          "cfgd": [{"Color": "Black"}],
          "subscribe": 0,
          "onlineInvLevels": {},
          "ss": 3,
          "ft": [0],
          "dp": "$69.88",
          "sva": [],
          "ds": 3,
          "mp": "$99.99",
          "mo": "2",
          "cls": 0,
          "n": "Braven 705 Portable Wireless Speaker - Black",
          "pid": "prod16880030",
          "se": [],
          "in": 422279,
          "clubInv": {},
          "ip": "",
          "li": "http://scene7.samsclub.com/is/image//samsclub/0081772901123_A",
          "equalPrice": 0,
          "prc": "1",
          "am": "",
          "frs": 1,
          "forceLogin": 0,
          "onlineInv": {
            "viewOnly": 0,
            "maxQty": 0,
            "status": 3,
            "minQty": 0,
            "in": 422279
          },
          "clubPrice": {},
          "pr": 5
        },
        {
          "vi": "http://scene7.samsclub.com/is/image/samsclub/0081772901126_S1",
          "moa": 2,
          "onlinePrice": {
            "smsglg": "",
            "showMsrp": 0,
            "ev": {},
            "msrpPrice": "",
            "ulpw": "$0.00",
            "suomplu": "",
            "finalPrice": "$69.88",
            "percentSaved": "",
            "suomsin": "",
            "iswti": 0,
            "pmns": "0",
            "listPrice": "$69.88",
            "smsgst": "",
            "pmxs": "0",
            "amountSaved": "",
            "pmsg": null,
            "savingType": ""
          },
          "ulpw": "$0.00",
          "id": "sku17664521",
          "cfgd": [{"Color": "Cyan"}],
          "subscribe": 0,
          "onlineInvLevels": {},
          "ss": 3,
          "ft": [0],
          "dp": "$69.88",
          "sva": [],
          "ds": 3,
          "mp": "$99.99",
          "mo": "2",
          "cls": 0,
          "n": "Braven 705 Portable Wireless Speaker - Cyan",
          "pid": "prod16880030",
          "se": [],
          "in": 422197,
          "clubInv": {},
          "ip": "",
          "li": "http://scene7.samsclub.com/is/image//samsclub/0081772901126_A",
          "equalPrice": 0,
          "prc": "1",
          "am": "",
          "frs": 1,
          "forceLogin": 0,
          "onlineInv": {
            "viewOnly": 0,
            "maxQty": 0,
            "status": 3,
            "minQty": 0,
            "in": 422197
          },
          "clubPrice": {},
          "pr": 5
        },
        {
          "vi": "http://scene7.samsclub.com/is/image/samsclub/0081772901130_S1",
          "moa": 2,
          "onlinePrice": {
            "smsglg": "",
            "showMsrp": 0,
            "ev": {},
            "msrpPrice": "",
            "ulpw": "$0.00",
            "suomplu": "",
            "finalPrice": "$69.88",
            "percentSaved": "",
            "suomsin": "",
            "iswti": 0,
            "pmns": "0",
            "listPrice": "$69.88",
            "smsgst": "",
            "pmxs": "0",
            "amountSaved": "",
            "pmsg": null,
            "savingType": ""
          },
          "ulpw": "$0.00",
          "id": "sku17664515",
          "cfgd": [{"Color": "Purple"}],
          "subscribe": 0,
          "onlineInvLevels": {},
          "ss": 0,
          "ft": [22],
          "dp": "$69.88",
          "sva": [],
          "ds": 0,
          "mp": "$99.99",
          "mo": "2",
          "cls": 0,
          "n": "Braven 705 Portable Wireless Speaker - Purple",
          "pid": "prod16880030",
          "se": [],
          "in": 422131,
          "clubInv": {},
          "ip": "",
          "li": "http://scene7.samsclub.com/is/image//samsclub/0081772901130_A",
          "equalPrice": 0,
          "prc": "1",
          "am": "",
          "frs": 1,
          "forceLogin": 0,
          "onlineInv": {
            "viewOnly": 0,
            "maxQty": 0,
            "status": 0,
            "minQty": 0,
            "in": 422131
          },
          "clubPrice": {},
          "pr": 5
        },
        {
          "vi": "http://scene7.samsclub.com/is/image/samsclub/0081772901125_S1",
          "moa": 2,
          "onlinePrice": {
            "smsglg": "",
            "showMsrp": 0,
            "ev": {},
            "msrpPrice": "",
            "ulpw": "$0.00",
            "suomplu": "",
            "finalPrice": "$69.88",
            "percentSaved": "",
            "suomsin": "",
            "iswti": 0,
            "pmns": "0",
            "listPrice": "$69.88",
            "smsgst": "",
            "pmxs": "0",
            "amountSaved": "",
            "pmsg": null,
            "savingType": ""
          },
          "ulpw": "$0.00",
          "id": "sku17664530",
          "cfgd": [{"Color": "White"}],
          "subscribe": 0,
          "onlineInvLevels": {},
          "ss": 0,
          "ft": [22],
          "dp": "$69.88",
          "sva": [],
          "ds": 0,
          "mp": "$99.99",
          "mo": "2",
          "cls": 0,
          "n": "Braven 705 Portable Wireless Speaker - White",
          "pid": "prod16880030",
          "se": [],
          "in": 422309,
          "clubInv": {},
          "ip": "",
          "li": "http://scene7.samsclub.com/is/image//samsclub/0081772901125_A",
          "equalPrice": 0,
          "prc": "1",
          "am": "",
          "frs": 1,
          "forceLogin": 0,
          "onlineInv": {
            "viewOnly": 0,
            "maxQty": 0,
            "status": 0,
            "minQty": 0,
            "in": 422309
          },
          "clubPrice": {},
          "pr": 5
        },
        {
          "vi": "http://scene7.samsclub.com/is/image/samsclub/0081772901127_S1",
          "moa": 2,
          "onlinePrice": {
            "smsglg": "",
            "showMsrp": 0,
            "ev": {},
            "msrpPrice": "",
            "ulpw": "$0.00",
            "suomplu": "",
            "finalPrice": "$69.88",
            "percentSaved": "",
            "suomsin": "",
            "iswti": 0,
            "pmns": "0",
            "listPrice": "$69.88",
            "smsgst": "",
            "pmxs": "0",
            "amountSaved": "",
            "pmsg": null,
            "savingType": ""
          },
          "ulpw": "$0.00",
          "id": "sku17664531",
          "cfgd": [{"Color": "Yellow"}],
          "subscribe": 0,
          "onlineInvLevels": {},
          "ss": 3,
          "ft": [0],
          "dp": "$69.88",
          "sva": [],
          "ds": 3,
          "mp": "$99.99",
          "mo": "2",
          "cls": 0,
          "n": "Braven 705 Portable Wireless Speaker - Yellow",
          "pid": "prod16880030",
          "se": [],
          "in": 422316,
          "clubInv": {},
          "ip": "",
          "li": "http://scene7.samsclub.com/is/image//samsclub/0081772901127_A",
          "equalPrice": 0,
          "prc": "1",
          "am": "",
          "frs": 1,
          "forceLogin": 0,
          "onlineInv": {
            "viewOnly": 0,
            "maxQty": 0,
            "status": 3,
            "minQty": 0,
            "in": 422316
          },
          "clubPrice": {},
          "pr": 5
        }
      ],
      "forceLogin": 0,
      "pc": {
        "cid": "1150109",
        "cnm": "Last Chance Buys"
      },
      "pmxs": "0",
      "pt": "NORMAL ITEM",
      "brand": "Braven",
      "ElectronicDelivery": "n",
      "isVariant": 1,
      "prodrid": "prod16880030"
    },
    {
      "startDate": "2014-09-26T03:57:36.632-05:00",
      "tn": "default",
      "evf": "0",
      "maxQty": 0,
      "itemFlag": "3",
      "promo": 0,
      "moa": 2,
      "ulpw": "$0.00",
      "prodid": "prod15890058",
      "endDate": null,
      "rc": 15,
      "suomsin": "",
      "id": "prod15890058",
      "iswti": 0,
      "pmns": "0",
      "ss": 3,
      "ft": [
        0,
        11
      ],
      "sva": [],
      "whyweloveit": "",
      "dp": "$97.86",
      "ds": 3,
      "mn": "BTW218",
      "mp": "",
      "mo": "4",
      "ev": [],
      "cls": 0,
      "isn": 0,
      "promoContent": "",
      "n": "Monster Tower of Music Speaker",
      "sd": "<ul>\n\t<li>3-way speakers with 270-degree sound<\/li>\n\t<li>Two 2.5&quot; side firing tweeters<\/li>\n\t<li>One 3&quot; front firing full range speaker<\/li>\n\t<li>Two 3&quot; side firing passive radiators<\/li>\n\t<li>20 watts of high fidelity sound<\/li>\n\t<li>Class-D Amplification for best performance<\/li>\n\t<li>Built-in rechargeable battery supports up to 8 hours of music<\/li>\n<\/ul>\n",
      "minQty": 0,
      "se": [],
      "suomplu": "",
      "ip": "",
      "cs": "0",
      "li": "http://scene7.samsclub.com/is/image//samsclub/0082739652512_A",
      "r": 4.7333,
      "ld": "<p>The Monster Tower of Music Speaker delivers your digital music with clarity, power and expandability. Our 3 speaker drivers and 2 passive radiators deliver a high lever clarity and range. With 20W of power, the audiophone will appreciate robust sound. With EZPLAY, you can expand up to 8 total speakers and listen to music all around you (additional speaker purchase required).<\/p>\n",
      "frs": 1,
      "sa": [{
        "vi": "",
        "moa": 2,
        "onlinePrice": {
          "smsglg": "",
          "showMsrp": 0,
          "ev": {},
          "msrpPrice": "",
          "ulpw": "$0.00",
          "suomplu": "",
          "finalPrice": "$97.86",
          "percentSaved": "",
          "suomsin": "",
          "iswti": 0,
          "pmns": "0",
          "listPrice": "$97.86",
          "smsgst": "",
          "pmxs": "0",
          "amountSaved": "",
          "pmsg": null,
          "savingType": ""
        },
        "ulpw": "$0.00",
        "id": "sku16404057",
        "cfgd": [],
        "subscribe": 0,
        "onlineInvLevels": {},
        "ss": 3,
        "ft": [
          0,
          11
        ],
        "dp": "$97.86",
        "sva": [],
        "ds": 3,
        "mp": "",
        "mo": "4",
        "cls": 0,
        "n": "Moster Tower of Music Speaker",
        "pid": "prod15890058",
        "se": [],
        "in": 64155,
        "clubInv": {
          "viewOnly": 0,
          "maxQty": 0,
          "status": 0,
          "minQty": 0,
          "in": 0
        },
        "ip": "",
        "li": "http://scene7.samsclub.com/is/image//samsclub/0082739652512_A",
        "equalPrice": 0,
        "prc": "15",
        "am": "",
        "frs": 1,
        "forceLogin": 0,
        "onlineInv": {
          "viewOnly": 0,
          "maxQty": 0,
          "status": 3,
          "minQty": 0,
          "in": 64155
        },
        "clubPrice": {},
        "pr": 4.7333
      }],
      "forceLogin": 0,
      "pc": {
        "cid": "1150109",
        "cnm": "Last Chance Buys"
      },
      "pmxs": "0",
      "pt": "NORMAL ITEM",
      "brand": "Monster",
      "ElectronicDelivery": "n",
      "isVariant": 0,
      "prodrid": "prod15890058"
    },
    {
      "startDate": null,
      "tn": "default",
      "evf": "0",
      "maxQty": 0,
      "itemFlag": "3",
      "promo": 0,
      "moa": 2,
      "ulpw": "$0.00",
      "prodid": "prod15800429",
      "endDate": null,
      "rc": 10,
      "suomsin": "",
      "id": "prod15800429",
      "iswti": 0,
      "pmns": "0",
      "ss": 3,
      "ft": [0],
      "sva": [],
      "whyweloveit": "<p>People just can&#39;t stop saying enough good things about the iHome iBT30 Bluetooth&reg; Speaker System. It&#39;s super compact&mdash;perfect when you&#39;re short on space&mdash;but has the sound of a full-rack stereo system with plenty of treble and bass. Charging is quick and incredibly easy with the nearly invisible base. But best of all, it works with virtually any Bluetooth-enabled device for true wireless portability that allows you to groove on the move.<\/p>\n",
      "dp": "$58.86",
      "ds": 3,
      "mn": "IBT30BC",
      "mp": "",
      "mo": "4",
      "ev": [],
      "cls": 0,
      "isn": 0,
      "promoContent": "",
      "n": "iHome iBT30 Bluetooth Speaker System",
      "sd": "\n<ul>\n\t<li>Wirelessly stream music from iPad, iPhone, iPod touch, Android, Blackberry and other Bluetooth-enabled devices<\/li>\n\t<li>USB port to charge mobile devices (charging cable not included)<\/li>\n\t<li>Internal rechargeable Lithium-ion battery (charging base included<\/li>\n\t<li>&nbsp;Reson8 speaker chamber technology and SRS TruBass for superior sound<\/li>\n\t<li>Aux-in jack to play audio from audio devices equipped with 3.5mm headphone jack (audio connection cable included)<\/li>\n\t<li>100V - 240V universal voltage AC adaptor<\/li>\n<\/ul>\n",
      "minQty": 0,
      "se": [],
      "suomplu": "",
      "ip": "",
      "cs": "0",
      "li": "http://scene7.samsclub.com/is/image//samsclub/0004753290154_A",
      "r": 4.6154,
      "ld": "<p>The iHome iBT30 Bluetooth Speaker System is a compact wireless speaker with a rechargeable lithium-ion battery that delivers big sound and is truly wireless. Features Bluetooth audio and stereo aware pairing to enable wireless stereo sound when linked with another compatible iHome speaker. The USB charging port allows the user to continue to list to their music while charging their device.<\/p>\n\n<p>&nbsp;<\/p>\n\n<p>&nbsp;<\/p>\n\n<h3 style=\"color: rgb(170, 170, 170); font-style: italic;\"><span style=\"font-size: 8px;\"><span style=\"font-family: calibri, sans-serif;\">Compare at Price is based on price of same or similar items on 05/20/15&nbsp;at online national retailers, excluding Walmart.com<\/span><\/span><\/h3>\n",
      "frs": 0,
      "sa": [{
        "vi": "",
        "moa": 2,
        "onlinePrice": {
          "smsglg": "",
          "showMsrp": 0,
          "ev": {},
          "msrpPrice": "",
          "ulpw": "$0.00",
          "suomplu": "",
          "finalPrice": "$58.86",
          "percentSaved": "",
          "suomsin": "",
          "iswti": 0,
          "pmns": "0",
          "listPrice": "$58.86",
          "smsgst": "",
          "pmxs": "0",
          "amountSaved": "",
          "pmsg": null,
          "savingType": ""
        },
        "ulpw": "$0.00",
        "id": "sku16314411",
        "cfgd": [],
        "subscribe": 0,
        "onlineInvLevels": {},
        "ss": 3,
        "ft": [0],
        "dp": "$58.86",
        "sva": [],
        "ds": 3,
        "mp": "",
        "mo": "4",
        "cls": 0,
        "n": "iHome Bluetooth Speaker System",
        "pid": "prod15800429",
        "se": [],
        "in": 31617,
        "clubInv": {},
        "ip": "",
        "li": "http://scene7.samsclub.com/is/image//samsclub/0004753290154_A",
        "equalPrice": 0,
        "prc": "10",
        "am": "",
        "frs": 0,
        "forceLogin": 0,
        "onlineInv": {
          "viewOnly": 0,
          "maxQty": 0,
          "status": 3,
          "minQty": 0,
          "in": 31617
        },
        "clubPrice": {},
        "pr": 4.6154
      }],
      "forceLogin": 0,
      "pc": {
        "cid": "11980103",
        "cnm": "Bluetooth Speakers"
      },
      "pmxs": "0",
      "pt": "NORMAL ITEM",
      "brand": "iHome",
      "ElectronicDelivery": "n",
      "isVariant": 0,
      "prodrid": "prod15800429"
    },
    {
      "startDate": "2015-01-20T01:09:16.424-06:00",
      "tn": "default",
      "evf": "0",
      "maxQty": 0,
      "itemFlag": "",
      "promo": 0,
      "moa": 2,
      "ulpw": "$0.00",
      "prodid": "prod17080284",
      "endDate": null,
      "rc": 0,
      "suomsin": "",
      "id": "prod17080284",
      "iswti": 0,
      "pmns": "0",
      "ss": 0,
      "ft": [
        22,
        11
      ],
      "sva": [],
      "whyweloveit": "",
      "dp": "$119.88",
      "ds": 0,
      "mn": "IPA56D",
      "mp": "",
      "mo": "4",
      "ev": [],
      "cls": 0,
      "isn": 0,
      "promoContent": "",
      "n": "Block Rocker Portable Bluetooth Speaker",
      "sd": "<ul>\n\t<li>Stream music wirelessly from any Bluetooth device up to 100 feet away<\/li>\n\t<li>Works w/ iPad, iPhone, Android, more<\/li>\n\t<li>Digital AM/FM radio w/ durable antenna<\/li>\n\t<li>Built-in rechargeable battery lasts up to 50 hrs<\/li>\n\t<li>Recessed wheels and telescoping handle for portability<\/li>\n\t<li>Easy Pair links your NFC-enabled smartphone or tablet with a simple tap<\/li>\n<\/ul>\n",
      "minQty": 0,
      "se": [],
      "suomplu": "",
      "ip": "",
      "cs": "0",
      "li": "http://scene7.samsclub.com/is/image//samsclub/0081271501646_A",
      "r": 0,
      "ld": "<p>Blast music wirelessly from smartphones, tablets, and more.<\/p>\n\n<p>Crank up your music whenever and wherever you want: Explorer Bluetooth is a powerful and flexible all-in-one sound system for mobile devices, MP3 players, microphones, and instruments. Explorer Bluetooth&#39;s wireless capability means you can keep your iPad, iPhone, Android or other Bluetooth music device right by your side as you blast your music. NFC-enabled smartphones or tablets can connect with just a simple tap using the Easy Pair feature.<\/p>\n\n<p>You can even listen to your favorite radio station or to the big game&mdash;just dial it in on Explorer Bluetooth&rsquo;s built-in AM/FM radio. The radio includes six presets so you can store your favorite radio stations. You can also plug in and crank up instruments, microphones and more. A high-quality microphone is included.<\/p>\n\n<p>With its built-in battery and charge indicator, Explorer Bluetooth lets you enjoy your music anywhere&mdash;indoors or outside&mdash;all day. A power cord is also included for nonstop music. You get powerful sound that&#39;s perfect for parties, BBQs, drive-in movies, family get-togethers, and more.<\/p>\n",
      "frs": 1,
      "sa": [{
        "vi": "",
        "moa": 2,
        "onlinePrice": {
          "smsglg": "Offer ends June 30 ",
          "showMsrp": 0,
          "ev": {
            "spmsg": "",
            "limit": 0,
            "cpn": "",
            "discountType": "0",
            "expiryDate": "Jun 30"
          },
          "msrpPrice": "",
          "ulpw": "$0.00",
          "suomplu": "",
          "finalPrice": "$119.88",
          "percentSaved": 0,
          "suomsin": "",
          "iswti": 0,
          "pmns": "0",
          "listPrice": "$149.88",
          "smsgst": "$30 off with Tech Savings",
          "pmxs": "0",
          "amountSaved": "$30.00",
          "pmsg": "Tech Savings items are limited to select items, availability, valid dates and limits per membership. Select Tech Savings are available online and in club. State and local laws may require sales tax to be charged on the pre-discounted price of an item with a Tech Savings offer. Available in the U.S., excluding Puerto Rico.",
          "savingType": "2"
        },
        "ulpw": "$0.00",
        "id": "sku17594288",
        "cfgd": [],
        "subscribe": 0,
        "onlineInvLevels": {},
        "ss": 0,
        "ft": [
          22,
          11
        ],
        "dp": "$119.88",
        "sva": [],
        "ds": 0,
        "mp": "",
        "mo": "4",
        "cls": 0,
        "n": "Block Rocker Portable Bluetooth Speaker",
        "pid": "prod17080284",
        "se": [],
        "in": 345233,
        "clubInv": {
          "viewOnly": 0,
          "maxQty": 0,
          "status": 0,
          "minQty": 0,
          "in": 0
        },
        "ip": "",
        "li": "http://scene7.samsclub.com/is/image//samsclub/0081271501646_A",
        "equalPrice": 0,
        "prc": "0",
        "am": "",
        "frs": 1,
        "forceLogin": 0,
        "onlineInv": {
          "viewOnly": 0,
          "maxQty": 0,
          "status": 0,
          "minQty": 0,
          "in": 345233
        },
        "clubPrice": {},
        "pr": 0
      }],
      "forceLogin": 0,
      "pc": {
        "cid": "11980103",
        "cnm": "Bluetooth Speakers"
      },
      "pmxs": "0",
      "pt": "NORMAL ITEM",
      "brand": "Ion",
      "ElectronicDelivery": "n",
      "isVariant": 0,
      "prodrid": "prod17080284"
    },
    {
      "startDate": "2015-03-21T03:28:03.672-05:00",
      "tn": "default",
      "evf": "0",
      "maxQty": 0,
      "itemFlag": "0",
      "promo": 0,
      "moa": 2,
      "ulpw": "$0.00",
      "prodid": "prod17690030",
      "endDate": null,
      "rc": 0,
      "suomsin": "",
      "id": "prod17690030",
      "iswti": 0,
      "pmns": "0",
      "ss": 3,
      "ft": [
        0,
        11
      ],
      "sva": [],
      "whyweloveit": "",
      "dp": "$129.88",
      "ds": 3,
      "mn": "BTW249",
      "mp": "",
      "mo": "4",
      "ev": [],
      "cls": 0,
      "isn": 0,
      "promoContent": "",
      "n": "Monster Wireless Indoor/Outdoor Speakers 40 Watt",
      "sd": "<p>The Monster BTW249 is an easily mountable speaker that can be used indoors and outdoors. The speakers are now equipped with EZ-Play Technology and are water/moisture resistant, offering a perfect sound in any environment. Not only does the speaker boast 40 Watts of explosive power, it also looks great. This speaker offers a new look, with an intense grill.<\/p>\n",
      "minQty": 0,
      "se": [],
      "suomplu": "",
      "ip": "",
      "cs": "0",
      "li": "http://scene7.samsclub.com/is/image//samsclub/0082739652634_A",
      "r": 0,
      "ld": "<p>Monster&trade; Indoor/Outdoor Speakers, take your audio anywhere! Stream all your favorite music wirelessly from your bluetooth device. With EZPlay technology, you can pair up to 4 more speaker pairs (8 speakers total) to completely surround yourself with music! With the weather resistant exterior, you can take your speakers to the lake or beach to provide you the best audio without the hassle of cables and wires! From your living room to bedroom to patio to garage to lake or beach, your Monster Speakers will go wherever you need them. There is also mounting holes for a more permanent enjoyment! (EZPlay also compatible with Monster BTX248BX (2014 model) and Monster Tower of Music).<\/p>\n",
      "frs": 1,
      "sa": [{
        "vi": "",
        "moa": 2,
        "onlinePrice": {
          "smsglg": "Offer ends July 31 ",
          "showMsrp": 0,
          "ev": {
            "spmsg": "",
            "limit": 0,
            "cpn": "",
            "discountType": "0",
            "expiryDate": "Jul 31"
          },
          "msrpPrice": "",
          "ulpw": "$0.00",
          "suomplu": "",
          "finalPrice": "$129.88",
          "percentSaved": 0,
          "suomsin": "",
          "iswti": 0,
          "pmns": "0",
          "listPrice": "$149.88",
          "smsgst": "$20 off with Tech Savings",
          "pmxs": "0",
          "amountSaved": "$20.00",
          "pmsg": "Tech Savings items are limited to select items, availability, valid dates and limits per membership. Select Tech Savings are available online and in club. State and local laws may require sales tax to be charged on the pre-discounted price of an item with a Tech Savings offer. Available in the U.S., excluding Puerto Rico.",
          "savingType": "2"
        },
        "ulpw": "$0.00",
        "id": "sku18204030",
        "cfgd": [],
        "subscribe": 0,
        "onlineInvLevels": {},
        "ss": 3,
        "ft": [
          0,
          11
        ],
        "dp": "$129.88",
        "sva": [],
        "ds": 3,
        "mp": "",
        "mo": "4",
        "cls": 0,
        "n": "Monster Wireless Indoor/Outdoor Speakers 40 Watt",
        "pid": "prod17690030",
        "se": [],
        "in": 622222,
        "clubInv": {
          "viewOnly": 0,
          "maxQty": 0,
          "status": 0,
          "minQty": 0,
          "in": 0
        },
        "ip": "",
        "li": "http://scene7.samsclub.com/is/image//samsclub/0082739652634_A",
        "equalPrice": 0,
        "prc": "0",
        "am": "",
        "frs": 1,
        "forceLogin": 0,
        "onlineInv": {
          "viewOnly": 0,
          "maxQty": 0,
          "status": 3,
          "minQty": 0,
          "in": 622222
        },
        "clubPrice": {},
        "pr": 0
      }],
      "forceLogin": 0,
      "pc": {
        "cid": "11400111",
        "cnm": "Sam's Exclusive"
      },
      "pmxs": "0",
      "pt": "NORMAL ITEM",
      "brand": "Monster",
      "ElectronicDelivery": "n",
      "isVariant": 0,
      "prodrid": "prod17690030"
    },
    {
      "startDate": "2015-04-08T03:59:59.122-05:00",
      "tn": "default",
      "evf": "0",
      "maxQty": 0,
      "itemFlag": "",
      "promo": 0,
      "moa": 2,
      "ulpw": "$0.00",
      "prodid": "prod17870197",
      "endDate": null,
      "rc": 0,
      "suomsin": "",
      "id": "prod17870197",
      "iswti": 0,
      "pmns": "0",
      "ss": 3,
      "ft": [
        0,
        11
      ],
      "sva": [],
      "whyweloveit": "",
      "dp": "$149.88",
      "ds": 3,
      "mn": "IMW576-BLU",
      "mp": "$199.00",
      "mo": "3",
      "ev": [],
      "cls": 0,
      "isn": 0,
      "promoContent": "",
      "n": "Altec Lansing Boom Jacket Speaker - Various Colors",
      "sd": "<ul>\n\t<li>Waterproof, sandproof, shockproof and snowproof construction<\/li>\n\t<li>Floatable and submersible<\/li>\n\t<li>40 hour battery life<\/li>\n<\/ul>\n",
      "minQty": 0,
      "se": [],
      "suomplu": "",
      "ip": "",
      "cs": "0",
      "li": "http://scene7.samsclub.com/is/image//samsclub/0002133196761_A",
      "r": 0,
      "ld": "<script language=\"JavaScript\" type=\"text/javascript\" src=\"http://admin.brightcove.com/js/BrightcoveExperiences.js\"><\/script><script type=\"text/javascript\">\nhead.ready(function(){\n\tvar videoId = '4258158607001';\n\tsetTimeout(function(){\n\t\t$('#pl-vertical-scroller').append('<div style=\"float:none; position:relative; top:45px;\"><a href=\"https://www.youtube.com/embed/GwSVyCDpH6o?list=PLA2HuUrXOsCKn0Al3-BajDU0XSb2vQy39&amp;rel=0&amp;showinfo=0\" class=\"newLink blueLinks video-thumbnail\"><img width=\"65\" height=\"65\" src=\"http://scene7.samsclub.com/is/image/samsclub/btnVIDEO?wid=65&amp;hei=65&amp;fmt=gif\"><\/a><\/div>');\n\t\t$(\".video-thumbnail\").click(function(){\n\t\t\t$(\"body\").append('<div id=\"video-modal\" style=\"width:853px;margin-left:-426px;top:160px;position:absolute;\"><a href=\"#close\" id=\"video-modal-close\" style=\"top:-21px;right:-21px;\"><\/a><object id=\"myExperience4244862006001\" class=\"BrightcoveExperience\"><param name=\"bgcolor\" value=\"#FFFFFF\" /><param name=\"width\" value=\"853\" /><param name=\"height\" value=\"480\" /><param name=\"playerID\" value=\"4176574989001\" /><param name=\"playerKey\" value=\"AQ~~,AAADzAU-A9E~,s0VuxCuix9CTXC5KhlLzx57c5MwnrvSp\" /><param name=\"isVid\" value=\"true\" /><param name=\"isUI\" value=\"true\" /><param name=\"dynamicStreaming\" value=\"true\" /><param name=\"@videoPlayer\" value=\"'+videoId+'\" /><\/object><\/div><div id=\"video-modal-backdrop\" class=\"modal-backdrop fade in\"><\/div>');\n\t\t\t\tbrightcove.createExperiences();\n\t\t\t$(\"#video-modal-close,#video-modal-backdrop\").click(function(){\n\t\t\t\t$(\"#video-modal,#video-modal-backdrop\").remove();\n\t\t\t\treturn false\n\t\t\t});\n\t\t\treturn false\n\t\t});\n\t},1500);\n});\n<\/script>\n<p>You live life to the fullest and you need a Bluetooth speaker that lives up to that same demand. The Boom Jacket has you covered. The IP67 rating means that it&nbsp;can go underwater up to 3&rsquo; for 30 minutes. Plus, it&nbsp;floats! Rock the days and nights away with 40 hours of battery life and the ability to recharge your smartphone or other portable devices. The Boom Jacket is so high tech, it not only talks to you (spoken caller ID and battery level) &nbsp;- but it also reacts to voice commands to answer or reject phone calls. Ultra-versatile with its mounting bracke,t you can secure the Boom Jacket&nbsp;wherever you want. The Aux In port lets you rock your tunes from any mobile music device with a headphone jack.<\/p>\n",
      "frs": 1,
      "sa": [
        {
          "vi": "http://scene7.samsclub.com/is/image/samsclub/0002133196761_S1",
          "moa": 2,
          "onlinePrice": {
            "smsglg": "",
            "showMsrp": 0,
            "ev": {},
            "msrpPrice": "",
            "ulpw": "$0.00",
            "suomplu": "",
            "finalPrice": "$149.88",
            "percentSaved": "",
            "suomsin": "",
            "iswti": 0,
            "pmns": "0",
            "listPrice": "$149.88",
            "smsgst": "",
            "pmxs": "0",
            "amountSaved": "",
            "pmsg": null,
            "savingType": ""
          },
          "ulpw": "$0.00",
          "id": "sku18384198",
          "cfgd": [{"Color": "Blue"}],
          "subscribe": 0,
          "onlineInvLevels": {},
          "ss": 3,
          "ft": [
            0,
            11
          ],
          "dp": "$149.88",
          "sva": [],
          "ds": 3,
          "mp": "$199.00",
          "mo": "3",
          "cls": 0,
          "n": "Altec Lansing Boom Jacket Speaker - Blue",
          "pid": "prod17870197",
          "se": [],
          "in": 699523,
          "clubInv": {
            "viewOnly": 0,
            "maxQty": 0,
            "status": 0,
            "minQty": 0,
            "in": 0
          },
          "ip": "",
          "li": "http://scene7.samsclub.com/is/image//samsclub/0002133196761_A",
          "equalPrice": 0,
          "prc": "0",
          "am": "",
          "frs": 1,
          "forceLogin": 0,
          "onlineInv": {
            "viewOnly": 0,
            "maxQty": 0,
            "status": 3,
            "minQty": 0,
            "in": 699523
          },
          "clubPrice": {},
          "pr": 0
        },
        {
          "vi": "http://scene7.samsclub.com/is/image/samsclub/0040648511849_S1",
          "moa": 2,
          "onlinePrice": {
            "smsglg": "",
            "showMsrp": 0,
            "ev": {},
            "msrpPrice": "",
            "ulpw": "$0.00",
            "suomplu": "",
            "finalPrice": "$168.88",
            "percentSaved": "",
            "suomsin": "",
            "iswti": 0,
            "pmns": "0",
            "listPrice": "$168.88",
            "smsgst": "",
            "pmxs": "0",
            "amountSaved": "",
            "pmsg": null,
            "savingType": ""
          },
          "ulpw": "$0.00",
          "id": "sku18964036",
          "cfgd": [{"Color": "Red"}],
          "subscribe": 0,
          "onlineInvLevels": {},
          "ss": 3,
          "ft": [
            0,
            11
          ],
          "dp": "$168.88",
          "sva": [],
          "ds": 3,
          "mp": "$199.00",
          "mo": "3",
          "cls": 0,
          "n": "Altec Lansing Boom Jacket Speaker - Red",
          "pid": "prod17870197",
          "se": [],
          "in": 851184,
          "clubInv": {
            "viewOnly": 0,
            "maxQty": 0,
            "status": 0,
            "minQty": 0,
            "in": 0
          },
          "ip": "",
          "li": "http://scene7.samsclub.com/is/image//samsclub/0040648511849_A",
          "equalPrice": 0,
          "prc": "0",
          "am": "",
          "frs": 1,
          "forceLogin": 0,
          "onlineInv": {
            "viewOnly": 0,
            "maxQty": 0,
            "status": 3,
            "minQty": 0,
            "in": 851184
          },
          "clubPrice": {},
          "pr": 0
        }
      ],
      "forceLogin": 0,
      "pc": {
        "cid": "9187",
        "cnm": "Patio Decor & Accessories"
      },
      "pmxs": "0",
      "pt": "NORMAL ITEM",
      "brand": "Altec Lansing",
      "ElectronicDelivery": "n",
      "isVariant": 1,
      "prodrid": "prod17870197"
    }
  ],
  "ci": "",
  "err": "",
  "pn": "1",
  "cso": "1",
  "ignorableError": [],
  "ps": "10"
}
